ESLocalIndi/DLI.py
ESLocalIndi/GWDLI.py
ESLocalIndi/GWKLI.py
ESLocalIndi/KLI.py
ESLocalIndi/__init__.py
ESLocalIndi/fig_heatmap.py
ESLocalIndi/sta_cal_sl.py
ESLocalIndi/sta_sig.py
eslocalindi-0.1.6.dist-info/METADATA
eslocalindi-0.1.6.dist-info/WHEEL
eslocalindi-0.1.6.dist-info/entry_points.txt
eslocalindi-0.1.6.dist-info/licenses/LICENSE
eslocalindi-0.1.6.dist-info/RECORD
