Metadata-Version: 2.4
Name: ESLocalIndi
Version: 0.1.6
Summary: The Package for Measuring Bivariate Spatial Association at the Local Level
License-File: LICENSE
Classifier: License :: OSI Approved :: MIT License
Classifier: Operating System :: OS Independent
Classifier: Programming Language :: Python :: 3
Requires-Python: >=3.10
Requires-Dist: matplotlib<4.0,>=3.4
Requires-Dist: numpy<2.0,>=1.21
Requires-Dist: pandas<2.3,>=1.3
Requires-Dist: scipy<2.0,>=1.1
Requires-Dist: seaborn<0.16,>=0.13
